jrpymlops/__init__.py
jrpymlops/__version__.py
jrpymlops/data/life_expectancy.zip
jrpymlops/data.py
jrpymlops-0.1.0.dist-info/METADATA
jrpymlops-0.1.0.dist-info/WHEEL
jrpymlops-0.1.0.dist-info/RECORD
