Metadata-Version: 2.1
Name: jrpymlops
Version: 0.1.0
Summary: Jumping Rivers: Introduction to Machine Learning Operations
Author: Jumping Rivers
Author-email: info@jumpingrivers.com
Requires-Python: >=3.9
Classifier: Programming Language :: Python :: 3
Classifier: Programming Language :: Python :: 3.9
Classifier: Programming Language :: Python :: 3.10
Classifier: Programming Language :: Python :: 3.11
Classifier: Programming Language :: Python :: 3.12
Requires-Dist: aiohttp (>=3.11.7,<4.0.0)
Requires-Dist: pins (>=0.8.6,<0.9.0)
Requires-Dist: plotly (>=5.24.1,<6.0.0)
Requires-Dist: pyyaml (>=6.0,<7.0)
Requires-Dist: requests (>=2.32.3,<3.0.0)
Requires-Dist: scikit-learn (>=1.1.1)
Requires-Dist: vetiver (>=0.2.5,<0.3.0)
